{
  "id": "MAP_LITTLEROOT_TOWN",
  "name": "LittlerootTown",
  "layout": "LAYOUT_LITTLEROOT_TOWN",
  "music": "MUS_LITTLEROOT",
  "region_map_section": "MAPSEC_LITTLEROOT_TOWN",
  "requires_flash": false,
  "weather": "WEATHER_SUNNY",
  "map_type": "MAP_TYPE_TOWN",
  "allow_cycling": true,
  "allow_escaping": false,
  "allow_running": true,
  "show_map_name": true,
  "battle_scene": "MAP_BATTLE_SCENE_NORMAL",
  "connections": [
    {
      "map": "MAP_ROUTE101",
      "offset": -8,
      "direction": "right"
    }
  ],
  "object_events": [
    {
      "local_id": "LOCALID_LITTLEROOT_TWIN",
      "graphics_id": "OBJ_EVENT_GFX_TWIN",
      "x": 11,
      "y": 36,
      "elevation": 3,
      "movement_type": "MOVEMENT_TYPE_WANDER_AROUND",
      "movement_range_x": 1,
      "movement_range_y": 2,
      "trainer_type": "TRAINER_TYPE_NONE",
      "trainer_sight_or_berry_tree_id": "0",
      "script": "LittlerootTown_EventScript_Twin",
      "flag": "0"
    },
    {
      "graphics_id": "OBJ_EVENT_GFX_BEAUTY",
      "x": 13,
      "y": 11,
      "elevation": 3,
      "movement_type": "MOVEMENT_TYPE_WANDER_AROUND",
      "movement_range_x": 2,
      "movement_range_y": 1,
      "trainer_type": "TRAINER_TYPE_NONE",
      "trainer_sight_or_berry_tree_id": "0",
      "script": "Columbus_NPC_Test_two",
      "flag": "FLAG_HIDE_LITTLEROOT_TOWN_FAT_MAN"
    },
    {
      "graphics_id": "OBJ_EVENT_GFX_BOY_1",
      "x": 17,
      "y": 11,
      "elevation": 3,
      "movement_type": "MOVEMENT_TYPE_WANDER_AROUND",
      "movement_range_x": 2,
      "movement_range_y": 1,
      "trainer_type": "TRAINER_TYPE_NONE",
      "trainer_sight_or_berry_tree_id": "0",
      "script": "LittlerootTown_EventScript_Boy",
      "flag": "0"
    },
    {
      "local_id": "LOCALID_LITTLEROOT_MOM",
      "graphics_id": "OBJ_EVENT_GFX_MOM",
      "x": 8,
      "y": 35,
      "elevation": 3,
      "movement_type": "MOVEMENT_TYPE_FACE_UP",
      "movement_range_x": 0,
      "movement_range_y": 0,
      "trainer_type": "TRAINER_TYPE_NONE",
      "trainer_sight_or_berry_tree_id": "0",
      "script": "LittlerootTown_EventScript_Mom",
      "flag": "FLAG_HIDE_LITTLEROOT_TOWN_MOM_OUTSIDE"
    },
    {
      "local_id": "LOCALID_LITTLEROOT_RIVAL",
      "graphics_id": "OBJ_EVENT_GFX_VAR_0",
      "x": 3,
      "y": 36,
      "elevation": 3,
      "movement_type": "MOVEMENT_TYPE_FACE_UP",
      "movement_range_x": 1,
      "movement_range_y": 1,
      "trainer_type": "TRAINER_TYPE_NONE",
      "trainer_sight_or_berry_tree_id": "0",
      "script": "0x0",
      "flag": "FLAG_HIDE_LITTLEROOT_TOWN_RIVAL"
    },
    {
      "local_id": "LOCALID_LITTLEROOT_BIRCH",
      "graphics_id": "OBJ_EVENT_GFX_PROF_BIRCH",
      "x": 4,
      "y": 36,
      "elevation": 3,
      "movement_type": "MOVEMENT_TYPE_FACE_UP",
      "movement_range_x": 1,
      "movement_range_y": 1,
      "trainer_type": "TRAINER_TYPE_NONE",
      "trainer_sight_or_berry_tree_id": "0",
      "script": "0x0",
      "flag": "FLAG_HIDE_LITTLEROOT_TOWN_BIRCH"
    },
    {
      "graphics_id": "OBJ_EVENT_GFX_ARTIST",
      "x": 15,
      "y": 13,
      "elevation": 3,
      "movement_type": "MOVEMENT_TYPE_WANDER_AROUND",
      "movement_range_x": 2,
      "movement_range_y": 1,
      "trainer_type": "TRAINER_TYPE_NONE",
      "trainer_sight_or_berry_tree_id": "0",
      "script": "LittlerootTown_EventScript_FatMan",
      "flag": "FLAG_HIDE_LITTLEROOT_TOWN_FAT_MAN"
    },
    {
      "graphics_id": "OBJ_EVENT_GFX_LIGHT_SPRITE",
      "x": 9,
      "y": 8,
      "elevation": 0,
      "movement_type": "MOVEMENT_TYPE_NONE",
      "movement_range_x": 0,
      "movement_range_y": 0,
      "trainer_type": "TRAINER_TYPE_NONE",
      "trainer_sight_or_berry_tree_id": "0",
      "script": "NULL",
      "flag": "0"
    },
    {
      "graphics_id": "OBJ_EVENT_GFX_LIGHT_SPRITE",
      "x": 13,
      "y": 16,
      "elevation": 0,
      "movement_type": "MOVEMENT_TYPE_NONE",
      "movement_range_x": 0,
      "movement_range_y": 0,
      "trainer_type": "TRAINER_TYPE_NONE",
      "trainer_sight_or_berry_tree_id": "0",
      "script": "NULL",
      "flag": "0"
    },
    {
      "graphics_id": "OBJ_EVENT_GFX_LIGHT_SPRITE",
      "x": 24,
      "y": 16,
      "elevation": 0,
      "movement_type": "MOVEMENT_TYPE_NONE",
      "movement_range_x": 0,
      "movement_range_y": 0,
      "trainer_type": "TRAINER_TYPE_NONE",
      "trainer_sight_or_berry_tree_id": "0",
      "script": "NULL",
      "flag": "0"
    },
    {
      "graphics_id": "OBJ_EVENT_GFX_LIGHT_SPRITE",
      "x": 29,
      "y": 8,
      "elevation": 0,
      "movement_type": "MOVEMENT_TYPE_NONE",
      "movement_range_x": 0,
      "movement_range_y": 0,
      "trainer_type": "TRAINER_TYPE_NONE",
      "trainer_sight_or_berry_tree_id": "0",
      "script": "NULL",
      "flag": "0"
    },
    {
      "graphics_id": "OBJ_EVENT_GFX_LIGHT_SPRITE",
      "x": 43,
      "y": 18,
      "elevation": 0,
      "movement_type": "MOVEMENT_TYPE_NONE",
      "movement_range_x": 0,
      "movement_range_y": 0,
      "trainer_type": "TRAINER_TYPE_NONE",
      "trainer_sight_or_berry_tree_id": "0",
      "script": "NULL",
      "flag": "0"
    },
    {
      "graphics_id": "OBJ_EVENT_GFX_CUTTABLE_TREE",
      "x": 22,
      "y": 10,
      "elevation": 3,
      "movement_type": "MOVEMENT_TYPE_LOOK_AROUND",
      "movement_range_x": 1,
      "movement_range_y": 1,
      "trainer_type": "TRAINER_TYPE_NONE",
      "trainer_sight_or_berry_tree_id": "0",
      "script": "EventScript_CutTree",
      "flag": "FLAG_TEMP_11"
    },
    {
      "graphics_id": "OBJ_EVENT_GFX_BREAKABLE_ROCK",
      "x": 26,
      "y": 10,
      "elevation": 3,
      "movement_type": "MOVEMENT_TYPE_LOOK_AROUND",
      "movement_range_x": 0,
      "movement_range_y": 0,
      "trainer_type": "TRAINER_TYPE_NONE",
      "trainer_sight_or_berry_tree_id": "0",
      "script": "EventScript_RockSmash",
      "flag": "FLAG_HIDE_RUSTURF_TUNNEL_ROCK_1"
    },
    {
      "graphics_id": "OBJ_EVENT_GFX_BREAKABLE_ROCK",
      "x": 26,
      "y": 10,
      "elevation": 3,
      "movement_type": "MOVEMENT_TYPE_LOOK_AROUND",
      "movement_range_x": 0,
      "movement_range_y": 0,
      "trainer_type": "TRAINER_TYPE_NONE",
      "trainer_sight_or_berry_tree_id": "0",
      "script": "EventScript_RockSmash",
      "flag": "FLAG_HIDE_RUSTURF_TUNNEL_ROCK_1"
    },
    {
      "graphics_id": "OBJ_EVENT_GFX_PUSHABLE_BOULDER",
      "x": 25,
      "y": 13,
      "elevation": 3,
      "movement_type": "MOVEMENT_TYPE_LOOK_AROUND",
      "movement_range_x": 0,
      "movement_range_y": 0,
      "trainer_type": "TRAINER_TYPE_NONE",
      "trainer_sight_or_berry_tree_id": "0",
      "script": "EventScript_StrengthBoulder",
      "flag": "FLAG_TEMP_12"
    },
    {
      "graphics_id": "OBJ_EVENT_GFX_SPECIES(TAILLOW)",
      "x": 18,
      "y": 6,
      "elevation": 4,
      "movement_type": "MOVEMENT_TYPE_WANDER_RIGHT_AND_LEFT",
      "movement_range_x": 4,
      "movement_range_y": 0,
      "trainer_type": "TRAINER_TYPE_BIRD",
      "trainer_sight_or_berry_tree_id": "0",
      "script": "NULL",
      "flag": "FLAG_TEMP_2"
    },
    {
      "graphics_id": "OBJ_EVENT_GFX_SPECIES(STARLY)",
      "x": 10,
      "y": 15,
      "elevation": 4,
      "movement_type": "MOVEMENT_TYPE_WANDER_RIGHT_AND_LEFT",
      "movement_range_x": 4,
      "movement_range_y": 0,
      "trainer_type": "TRAINER_TYPE_BIRD",
      "trainer_sight_or_berry_tree_id": "0",
      "script": "NULL",
      "flag": "FLAG_TEMP_4"
    },
    {
      "graphics_id": "OBJ_EVENT_GFX_SPECIES(STARLY)",
      "x": 43,
      "y": 4,
      "elevation": 4,
      "movement_type": "MOVEMENT_TYPE_WANDER_RIGHT_AND_LEFT",
      "movement_range_x": 4,
      "movement_range_y": 0,
      "trainer_type": "TRAINER_TYPE_BIRD",
      "trainer_sight_or_berry_tree_id": "0",
      "script": "NULL",
      "flag": "FLAG_TEMP_3"
    },
    {
      "graphics_id": "OBJ_EVENT_GFX_SPECIES(FLETCHLING)",
      "x": 33,
      "y": 7,
      "elevation": 4,
      "movement_type": "MOVEMENT_TYPE_LOOK_AROUND",
      "movement_range_x": 4,
      "movement_range_y": 0,
      "trainer_type": "TRAINER_TYPE_BIRD",
      "trainer_sight_or_berry_tree_id": "0",
      "script": "NULL",
      "flag": "FLAG_TEMP_1"
    }
  ],
  "warp_events": [
    {
      "x": 17,
      "y": 8,
      "elevation": 0,
      "dest_map": "MAP_RUSTBORO_CITY_GYM",
      "dest_warp_id": "0"
    },
    {
      "x": 7,
      "y": 7,
      "elevation": 0,
      "dest_map": "MAP_COLUMBUS_PLAYER_HOUSE_F1",
      "dest_warp_id": "1"
    },
    {
      "x": 44,
      "y": 7,
      "elevation": 0,
      "dest_map": "MAP_LITTLEROOT_TOWN",
      "dest_warp_id": "3"
    },
    {
      "warp_id": "NewLab",
      "x": 31,
      "y": 9,
      "elevation": 0,
      "dest_map": "MAP_NEWER_HOUSE",
      "dest_warp_id": "0"
    },
    {
      "x": 9,
      "y": 17,
      "elevation": 0,
      "dest_map": "MAP_SPROUT_TOWN_HOUSE",
      "dest_warp_id": "0"
    },
    {
      "x": 21,
      "y": 17,
      "elevation": 0,
      "dest_map": "MAP_SPROUT_PC_F1",
      "dest_warp_id": "0"
    }
  ],
  "coord_events": [
    {
      "type": "trigger",
      "x": 27,
      "y": 22,
      "elevation": 0,
      "var": "VAR_COLUMBUS_INTRO_STATE",
      "var_value": "0",
      "script": "Columbus_Trigger_BlockPath"
    }
  ],
  "bg_events": [
    {
      "type": "sign",
      "x": 2,
      "y": 10,
      "elevation": 0,
      "player_facing_dir": "BG_EVENT_PLAYER_FACING_ANY",
      "script": "LittlerootTown_EventScript_TownSign"
    },
    {
      "type": "sign",
      "x": 43,
      "y": 8,
      "elevation": 0,
      "player_facing_dir": "BG_EVENT_PLAYER_FACING_ANY",
      "script": "LittlerootTown_EventScript_BirchsLabSign"
    },
    {
      "type": "sign",
      "x": 3,
      "y": 10,
      "elevation": 3,
      "player_facing_dir": "BG_EVENT_PLAYER_FACING_ANY",
      "script": "LittlerootTown_EventScript_BrendansHouseSign"
    },
    {
      "type": "sign",
      "x": 22,
      "y": 17,
      "elevation": 3,
      "player_facing_dir": "BG_EVENT_PLAYER_FACING_ANY",
      "script": "LittlerootTown_EventScript_MaysHouseSign"
    },
    {
      "type": "sign",
      "x": 45,
      "y": 4,
      "elevation": 0,
      "player_facing_dir": "BG_EVENT_PLAYER_FACING_ANY",
      "script": "NULL"
    },
    {
      "type": "sign",
      "x": 12,
      "y": 8,
      "elevation": 0,
      "player_facing_dir": "BG_EVENT_PLAYER_FACING_ANY",
      "script": "LittlerootTown_EventScript_NewSign"
    },
    {
      "type": "sign",
      "x": 39,
      "y": 20,
      "elevation": 0,
      "player_facing_dir": "BG_EVENT_PLAYER_FACING_NORTH",
      "script": "LittlerootTown_EventScript_TownSign"
    },
    {
      "type": "sign",
      "x": 11,
      "y": 8,
      "elevation": 0,
      "player_facing_dir": "BG_EVENT_PLAYER_FACING_ANY",
      "script": "Columbus_NPC_Test"
    }
  ]
}
